limbo/__init__.py
limbo/data.py
limbo/cli/__init__.py
limbo/cli/compress.py
limbo/cli/lint.py
limbo/cli/materialize.py
limbo/cli/stats.py
limbo_ml-0.4.0.dist-info/entry_points.txt
limbo_ml-0.4.0.dist-info/LICENSE
limbo_ml-0.4.0.dist-info/WHEEL
limbo_ml-0.4.0.dist-info/METADATA
limbo_ml-0.4.0.dist-info/RECORD
